{
  "days": [
    {
      "id": "1",
      "day": 1
    },
    {
      "id": "2",
      "day": 2
    },
    {
      "id": "3",
      "day": 3
    },
    {
      "id": "6950",
      "day": 4
    }
  ],
  "words": [
    {
      "id": "1",
      "day": 1,
      "eng": "book",
      "kor": "책",
      "isDone": true
    },
    {
      "id": "3",
      "day": 2,
      "eng": "car",
      "kor": "자동차",
      "isDone": false
    },
    {
      "id": "4",
      "day": 2,
      "eng": "pen",
      "kor": "펜",
      "isDone": false
    },
    {
      "id": "5",
      "day": 3,
      "eng": "school",
      "kor": "학교",
      "isDone": false
    },
    {
      "id": "6",
      "day": 3,
      "eng": "pencil",
      "kor": "연필",
      "isDone": false
    },
    {
      "id": "d494",
      "day": "3",
      "eng": "computer",
      "kor": "커뮤터",
      "isDone": false
    },
    {
      "id": "b9d9",
      "day": "4",
      "eng": "mouse",
      "kor": "쥐",
      "isDone": false
    }
  ]
}
